mcp_server_template/__init__.py
mcp_server_template/cli.py
mcp_server_template/py.typed
mcp_server_template/server.py
mcp_server_template-0.1.1.dist-info/METADATA
mcp_server_template-0.1.1.dist-info/WHEEL
mcp_server_template-0.1.1.dist-info/entry_points.txt
mcp_server_template-0.1.1.dist-info/licenses/LICENSE
mcp_server_template-0.1.1.dist-info/RECORD
