Metadata-Version: 2.4
Name: mcp-server-template
Version: 0.1.1
Author-email: narumi <toucans-cutouts0f@icloud.com>
License-File: LICENSE
Requires-Python: >=3.12
Requires-Dist: loguru>=0.7.3
Requires-Dist: mcp>=1.6.0
